Metadata-Version: 2.1
Name: mdataio
Version: 0.1.4
Summary: scripts used for meidcal data manipulation
Home-page: https://xinario.github.io
Author: Xin Yi
License: UNKNOWN
Download-URL: https://github.com/xinario/mdataio/archive/refs/tags/0.1.4.tar.gz
Platform: UNKNOWN
Classifier: Programming Language :: Python :: 3
Classifier: License :: OSI Approved :: MIT License
Classifier: Operating System :: OS Independent
